solrbackup-0.1.dist-info/METADATA
solrbackup-0.1.dist-info/DESCRIPTION.rst
solrbackup-0.1.dist-info/top_level.txt
solrbackup-0.1.dist-info/metadata.json
solrbackup-0.1.dist-info/RECORD
solrbackup-0.1.dist-info/WHEEL
solrbackup/__init__.py
solrbackup/solrbackup.py
