Metadata-Version: 2.0
Name: solrbackup
Version: 0.1
Summary: Python script for backing up a remote Solr 4 core or SolrCloud cluster
Home-page: https://github.com/nla/solrbackup
Author: National Library of Australia
Author-email: ato@meshy.org
License: MIT
Platform: UNKNOWN
